arlas_city_api_python/__init__.py
arlas_city_api_python/api_client.py
arlas_city_api_python/configuration.py
arlas_city_api_python/rest.py
arlas_city_api_python/apis/__init__.py
arlas_city_api_python/apis/data_api.py
arlas_city_api_python/apis/process_api.py
arlas_city_api_python/models/__init__.py
arlas_city_api_python/models/archive.py
arlas_city_api_python/models/bbox.py
arlas_city_api_python/models/collection_reference.py
arlas_city_api_python/models/collection_reference_parameters.py
arlas_city_api_python/models/dublin_core_element_name.py
arlas_city_api_python/models/error.py
arlas_city_api_python/models/expression.py
arlas_city_api_python/models/feed.py
arlas_city_api_python/models/feed_statistics.py
arlas_city_api_python/models/filter.py
arlas_city_api_python/models/generator.py
arlas_city_api_python/models/inspire.py
arlas_city_api_python/models/inspire_limitation_access.py
arlas_city_api_python/models/inspire_spatial_resolution.py
arlas_city_api_python/models/inspire_uri.py
arlas_city_api_python/models/issues_details.py
arlas_city_api_python/models/job.py
arlas_city_api_python/models/job_order.py
arlas_city_api_python/models/keyword.py
arlas_city_api_python/models/number.py
arlas_city_api_python/models/open_search.py
arlas_city_api_python/models/person.py
arlas_city_api_python/models/raster_tile_url.py
arlas_city_api_python/models/step.py
arlas_city_api_python/models/validation_report.py
arlas_city_api_python/models/validation_results.py
test/__init__.py
test/test_archive.py
test/test_bbox.py
test/test_collection_reference.py
test/test_collection_reference_parameters.py
test/test_data_api.py
test/test_dublin_core_element_name.py
test/test_error.py
test/test_expression.py
test/test_feed.py
test/test_feed_statistics.py
test/test_filter.py
test/test_generator.py
test/test_inspire.py
test/test_inspire_limitation_access.py
test/test_inspire_spatial_resolution.py
test/test_inspire_uri.py
test/test_issues_details.py
test/test_job.py
test/test_job_order.py
arlas_city_api-0.1.0.dist-info/METADATA
arlas_city_api-0.1.0.dist-info/WHEEL
arlas_city_api-0.1.0.dist-info/top_level.txt
arlas_city_api-0.1.0.dist-info/RECORD
